llm_ner_nel/__init__.py
llm_ner_nel/core/__init__.py
llm_ner_nel/core/dto.py
llm_ner_nel/evaluation/__init__.py
llm_ner_nel/evaluation/evaluate.py
llm_ner_nel/evaluation/main.py
llm_ner_nel/inference_api/__init__.py
llm_ner_nel/inference_api/entity_inference.py
llm_ner_nel/inference_api/llm_config.py
llm_ner_nel/inference_api/mlflow_config.py
llm_ner_nel/inference_api/prompts.py
llm_ner_nel/inference_api/relationship_inference.py
llm_ner_nel/inference_api/strategies/base.py
llm_ner_nel/inference_api/strategies/google_ai_studio.py
llm_ner_nel/inference_api/strategies/gpt_oss.py
llm_ner_nel/inference_api/strategies/ollama.py
llm_ner_nel/inference_api/strategies/ollama_slim.py
llm_ner_nel/inference_api/strategies/openai.py
llm_ner_nel/inference_api/strategies/strategy_factory.py
llm_ner_nel/knowledge_graph/__init__.py
llm_ner_nel/knowledge_graph/graph.py
llm_ner_nel/knowledge_graph/neo_db_config.py
llm_ner_nel-0.5.0.dist-info/licenses/LICENSE
llm_ner_nel-0.5.0.dist-info/METADATA
llm_ner_nel-0.5.0.dist-info/WHEEL
llm_ner_nel-0.5.0.dist-info/top_level.txt
llm_ner_nel-0.5.0.dist-info/RECORD
