Metadata-Version: 2.4
Name: llm_ner_nel
Version: 0.5.0
Summary: Use an LLM to run inference, for NER (named entity recognition) and/or NEL (named entity linking). Build a knowledge graph. Evaluate results.
Author: Paul Eger
Project-URL: homepage, https://github.com/egerpaulj/LlmKnowledgeGraph
Project-URL: repository, https://github.com/egerpaulj/LlmKnowledgeGraph.git
Requires-Python: >=3.10.16
License-File: LICENSE
Requires-Dist: typing
Requires-Dist: py2neo
Requires-Dist: pydantic
Requires-Dist: ollama
Requires-Dist: pika
Requires-Dist: prometheus_client
Requires-Dist: psutil
Requires-Dist: pymongo
Requires-Dist: mlflow
Requires-Dist: openai
Requires-Dist: google-genai
Requires-Dist: tenacity
Dynamic: license-file
